pydantic_resolve/__init__.py
pydantic_resolve/analysis.py
pydantic_resolve/constant.py
pydantic_resolve/exceptions.py
pydantic_resolve/loader_manager.py
pydantic_resolve/resolver.py
pydantic_resolve/utils/__init__.py
pydantic_resolve/utils/class_util.py
pydantic_resolve/utils/collector.py
pydantic_resolve/utils/conversion.py
pydantic_resolve/utils/dataloader.py
pydantic_resolve/utils/depend.py
pydantic_resolve/utils/er_diagram.py
pydantic_resolve/utils/expose.py
pydantic_resolve/utils/logger.py
pydantic_resolve/utils/meta.py
pydantic_resolve/utils/openapi.py
pydantic_resolve/utils/params.py
pydantic_resolve/utils/profile.py
pydantic_resolve/utils/resolver_configurator.py
pydantic_resolve/utils/subset.py
pydantic_resolve/utils/types.py
pydantic_resolve-2.4.7.dist-info/METADATA
pydantic_resolve-2.4.7.dist-info/WHEEL
pydantic_resolve-2.4.7.dist-info/licenses/LICENSE
pydantic_resolve-2.4.7.dist-info/RECORD
