Metadata-Version: 2.4
Name: pydantic-resolve
Version: 2.4.7
Summary: pydantic-resolve turns pydantic from a static data container into a powerful composable component.
Project-URL: Repository, https://github.com/allmonday/pydantic_resolve
Author-email: tangkikodo <allmonday@126.com>
License: MIT
License-File: LICENSE
Keywords: dataloader,pydantic,resolver
Classifier: Development Status :: 5 - Production/Stable
Classifier: Framework :: FastAPI
Classifier: Framework :: Pydantic
Classifier: Intended Audience :: Developers
Classifier: License :: OSI Approved :: MIT License
Classifier: Programming Language :: Python :: 3
Classifier: Programming Language :: Python :: 3.10
Classifier: Programming Language :: Python :: 3.11
Classifier: Programming Language :: Python :: 3.12
Classifier: Programming Language :: Python :: 3.13
Classifier: Programming Language :: Python :: 3.14
Classifier: Topic :: Internet :: WWW/HTTP :: HTTP Servers
Classifier: Topic :: Software Development :: Libraries :: Python Modules
Requires-Python: >=3.10
Requires-Dist: aiodataloader<0.5.0,>=0.4.0
Provides-Extra: dev
Requires-Dist: aiosqlite<0.19.0,>=0.18.0; extra == 'dev'
Requires-Dist: coverage<8.0.0,>=7.2.1; extra == 'dev'
Requires-Dist: mkdocs-material<10,>=9; extra == 'dev'
Requires-Dist: mkdocs-static-i18n[material]==1.2.0; extra == 'dev'
Requires-Dist: psutil<8.0.0,>=7.1.0; extra == 'dev'
Requires-Dist: pydantic<3.0.0,>=2.12.0; extra == 'dev'
Requires-Dist: pytest-asyncio<0.22.0,>=0.21.0; extra == 'dev'
Requires-Dist: pytest-benchmark[histogram]>=5.0.1; extra == 'dev'
Requires-Dist: pytest-cov<5.0.0,>=4.0.0; extra == 'dev'
Requires-Dist: pytest<8.0.0,>=7.2.2; extra == 'dev'
Requires-Dist: ruff<0.15.0,>=0.14.5; extra == 'dev'
Requires-Dist: sqlalchemy[asyncio]<3.0.0,>=2.0.7; extra == 'dev'
Requires-Dist: tox<5.0.0,>=4.4.6; extra == 'dev'
